LICENSE
MANIFEST.in
README.md
pyproject.toml
requirements.txt
setup.py
connectome/__init__.py
connectome/__version__.py
connectome/exceptions.py
connectome/serializers.py
connectome/utils.py
connectome.egg-info/PKG-INFO
connectome.egg-info/SOURCES.txt
connectome.egg-info/dependency_links.txt
connectome.egg-info/requires.txt
connectome.egg-info/top_level.txt
connectome/cache/__init__.py
connectome/cache/base.py
connectome/cache/disk.py
connectome/cache/memory.py
connectome/containers/__init__.py
connectome/containers/base.py
connectome/containers/context.py
connectome/containers/reversible.py
connectome/engine/__init__.py
connectome/engine/base.py
connectome/engine/compiler.py
connectome/engine/edges.py
connectome/engine/graph.py
connectome/engine/node_hash.py
connectome/engine/utils.py
connectome/engine/vm.py
connectome/interface/__init__.py
connectome/interface/blocks.py
connectome/interface/complex_edges.py
connectome/interface/decorators.py
connectome/interface/edges.py
connectome/interface/external.py
connectome/interface/factory.py
connectome/interface/factory_utils.py
connectome/interface/metaclasses.py
connectome/interface/nodes.py
connectome/interface/split.py
connectome/interface/utils.py
connectome/layers/__init__.py
connectome/layers/apply.py
connectome/layers/base.py
connectome/layers/cache.py
connectome/layers/chain.py
connectome/layers/check_ids.py
connectome/layers/columns.py
connectome/layers/debug.py
connectome/layers/dynamic.py
connectome/layers/filter.py
connectome/layers/group.py
connectome/layers/join.py
connectome/layers/merge.py
connectome/layers/split.py