Metadata-Version: 2.1
Name: connectome
Version: 0.10.0
Summary: A library for datasets containing heterogeneous data
Home-page: https://github.com/neuro-ml/connectome
Download-URL: https://github.com/neuro-ml/connectome/archive/v0.10.0.tar.gz
Author: NeuroML Group
Author-email: NeuroML Group <max@ira-labs.com>
License:                                  Apache License
Project-URL: Homepage, https://github.com/neuro-ml/connectome
Project-URL: Issues, https://github.com/neuro-ml/connectome/issues
Project-URL: Source, https://github.com/neuro-ml/connectome
Project-URL: Docs, https://neuro-ml.github.io/connectome
Keywords: dag,dataset,cache,consistency
Classifier: Development Status :: 4 - Beta
Classifier: License :: OSI Approved :: Apache Software License
Classifier: Programming Language :: Python :: 3
Classifier: Programming Language :: Python :: 3.7
Classifier: Programming Language :: Python :: 3.8
Classifier: Programming Language :: Python :: 3.9
Classifier: Programming Language :: Python :: 3.10
Classifier: Programming Language :: Python :: 3.11
Classifier: Programming Language :: Python :: 3 :: Only
Requires-Python: >=3.7
License-File: LICENSE
